Lgk/__init__.py
Lgk-1.10.dist-info/LICENSE.py
Lgk-1.10.dist-info/METADATA
Lgk-1.10.dist-info/WHEEL
Lgk-1.10.dist-info/top_level.txt
Lgk-1.10.dist-info/RECORD
