Metadata-Version: 2.1
Name: Lgk
Version: 1.10
Summary: Description: just write Lgk.Help()
Home-page: UNKNOWN
Author: BT Ansixs
Author-email: noobra24l8w@gmail.com
License: LICENSE
Platform: UNKNOWN
License-File: LICENSE.py
